statusboard/__init__.py
statusboard/admin.py
statusboard/apps.py
statusboard/forms.py
statusboard/models.py
statusboard/serializers.py
statusboard/settings.py
statusboard/urls.py
statusboard/views.py
statusboard/locale/it/LC_MESSAGES/django.mo
statusboard/locale/it/LC_MESSAGES/django.po
statusboard/migrations/0001_initial.py
statusboard/migrations/0002_incident.py
statusboard/migrations/0003_auto_20170121_2030.py
statusboard/migrations/0003_auto_20170125_0604.py
statusboard/migrations/0004_incident_occurred.py
statusboard/migrations/0005_merge.py
statusboard/migrations/0006_maintenance.py
statusboard/migrations/0007_auto_20170213_1114.py
statusboard/migrations/0008_servicegroup_collapse.py
statusboard/migrations/0009_auto_20170217_0749.py
statusboard/migrations/0009_servicegroup_position.py
statusboard/migrations/0010_auto_20170217_0835.py
statusboard/migrations/0011_auto_20170217_1120.py
statusboard/migrations/0012_auto_20170217_1322.py
statusboard/migrations/0013_auto_20170220_1444.py
statusboard/migrations/0014_incident_closed.py
statusboard/migrations/0014_merge_20170222_2054.py
statusboard/migrations/0015_close_previously_fixed_incidents.py
statusboard/migrations/0015_merge_20170222_2058.py
statusboard/migrations/0016_auto_20170223_1005.py
statusboard/migrations/0016_service_position.py
statusboard/migrations/0017_auto_20170223_1428.py
statusboard/migrations/0018_merge_20170223_1429.py
statusboard/migrations/0019_auto_20170223_1503.py
statusboard/migrations/0020_auto_20170223_1651.py
statusboard/migrations/0021_auto_20201204_0846.py
statusboard/migrations/0022_auto_20201204_0856.py
statusboard/migrations/__init__.py
statusboard/static/statusboard/css/bootstrap-icons.css
statusboard/static/statusboard/css/bootstrap.min.css
statusboard/static/statusboard/css/bootstrap.min.css.map
statusboard/static/statusboard/css/statusboard.css
statusboard/static/statusboard/css/fonts/bootstrap-icons.woff
statusboard/static/statusboard/css/fonts/bootstrap-icons.woff2
django_statusboard-0.15.1.dist-info/LICENSE
django_statusboard-0.15.1.dist-info/METADATA
django_statusboard-0.15.1.dist-info/WHEEL
django_statusboard-0.15.1.dist-info/top_level.txt
django_statusboard-0.15.1.dist-info/RECORD
